{
  "project_info": {
    "project_number": "577353451528",
    "project_id": "shoppy-ad8b0",
    "storage_bucket": "shoppy-ad8b0.appspot.com"
  },
  "client": [
    {
      "client_info": {
        "mobilesdk_app_id": "1:577353451528:android:557d3ce93f1ebdcd54e9bd",
        "android_client_info": {
          "package_name": "com.project.shoppy"
        }
      },
      "oauth_client": [
        {
          "client_id": "577353451528-2gsusjuv20uanjg2mr0tdhd1io3vvoeu.apps.googleusercontent.com",
          "client_type": 3
        }
      ],
      "api_key": [
        {
          "current_key": "AIzaSyBR-Y7vacNl6whCM3uJMPzfv85ZXGR4SEU"
        }
      ],
      "services": {
        "appinvite_service": {
          "other_platform_oauth_client": [
            {
              "client_id": "577353451528-2gsusjuv20uanjg2mr0tdhd1io3vvoeu.apps.googleusercontent.com",
              "client_type": 3
            }
          ]
        }
      }
    },
    {
      "client_info": {
        "mobilesdk_app_id": "1:577353451528:android:3ada3e4e8c3ac79f54e9bd",
        "android_client_info": {
          "package_name": "com.project.shoppy_seller"
        }
      },
      "oauth_client": [
        {
          "client_id": "577353451528-2gsusjuv20uanjg2mr0tdhd1io3vvoeu.apps.googleusercontent.com",
          "client_type": 3
        }
      ],
      "api_key": [
        {
          "current_key": "AIzaSyBR-Y7vacNl6whCM3uJMPzfv85ZXGR4SEU"
        }
      ],
      "services": {
        "appinvite_service": {
          "other_platform_oauth_client": [
            {
              "client_id": "577353451528-2gsusjuv20uanjg2mr0tdhd1io3vvoeu.apps.googleusercontent.com",
              "client_type": 3
            }
          ]
        }
      }
    }
  ],
  "configuration_version": "1"
}